LICENSE.md
MANIFEST.in
README.md
requirements.txt
setup.py
testbox/__init__.py
testbox.egg-info/PKG-INFO
testbox.egg-info/SOURCES.txt
testbox.egg-info/dependency_links.txt
testbox.egg-info/requires.txt
testbox.egg-info/top_level.txt