Metadata-Version: 2.1
Name: testbox
Version: 1.0.4
Summary: Test/TAS framework for DOSBox
Home-page: https://github.com/excitoon/testbox
Author: Vladimir Chebotarev
Author-email: vladimir.chebotarev@gmail.com
License: MIT
Project-URL: Documentation, https://github.com/excitoon/testbox/blob/master/README.md
Project-URL: Source, https://github.com/excitoon/testbox
Project-URL: Tracker, https://github.com/excitoon/testbox/issues
Keywords: dosbox,test,tas
Classifier: Development Status :: 5 - Production/Stable
Classifier: Intended Audience :: Developers
Classifier: License :: OSI Approved :: MIT License
Classifier: Operating System :: OS Independent
Classifier: Programming Language :: Python :: 3 :: Only
License-File: LICENSE.md
Requires-Dist: pillow
